mdx_custom_span_class.py
setup.py
mdx_customspanclass.egg-info/PKG-INFO
mdx_customspanclass.egg-info/SOURCES.txt
mdx_customspanclass.egg-info/dependency_links.txt
mdx_customspanclass.egg-info/requires.txt
mdx_customspanclass.egg-info/top_level.txt