Metadata-Version: 1.1
Name: mdx-customspanclass
Version: 1.1.1
Summary: Markdown extension which allows inserting span elements with custom class
Home-page: https://github.com/grinich/mdx_custom_span_class
Author: Konrad Wasowicz
Author-email: exaroth@gmail.com
License: UNKNOWN
Platform: UNKNOWN
Classifier: Development Status :: 4 - Beta
Classifier: Operating System :: OS Independent
Classifier: License :: OSI Approved :: BSD License
Classifier: Intended Audience :: Developers
Classifier: Environment :: Web Environment
Classifier: Programming Language :: Python
Classifier: Topic :: Text Processing :: Filters
Classifier: Topic :: Text Processing :: Markup :: HTML
